sa_gwdata/__init__.py
sa_gwdata/identifiers.py
sa_gwdata/local_cache.py
sa_gwdata/sarig.py
sa_gwdata/waterconnect.py
sa_gwdata/waterconnect_funcs.py
python_sa_gwdata-0.14.dist-info/LICENSE
python_sa_gwdata-0.14.dist-info/METADATA
python_sa_gwdata-0.14.dist-info/WHEEL
python_sa_gwdata-0.14.dist-info/top_level.txt
python_sa_gwdata-0.14.dist-info/RECORD
