Metadata-Version: 2.1
Name: python-sa-gwdata
Version: 0.14
Summary: Unofficial Python package to ease access to groundwater data in South Australia
Home-page: https://github.com/kinverarity1/python-sa-gwdata
Author: Kent Inverarity
Author-email: kinverarity@hotmail.com
License: MIT
Keywords: groundwater data
Classifier: Programming Language :: Python :: 3.6
Classifier: Programming Language :: Python :: 3.7
Requires-Python: >=3.6
License-File: LICENSE
Requires-Dist: requests
Requires-Dist: pandas >=0.24.1
Requires-Dist: platformdirs
Requires-Dist: pyarrow
Requires-Dist: pyshp
Provides-Extra: all
Requires-Dist: pytest >=3.6 ; extra == 'all'
Requires-Dist: pytest-cov ; extra == 'all'
Requires-Dist: coverage ; extra == 'all'
Requires-Dist: codecov ; extra == 'all'
Requires-Dist: pytest-benchmark ; extra == 'all'
Requires-Dist: black ; extra == 'all'
Requires-Dist: sphinx ; extra == 'all'
Requires-Dist: nbsphinx ; extra == 'all'
Requires-Dist: shapely ; extra == 'all'
Requires-Dist: contextily ; extra == 'all'
Requires-Dist: geopandas ; extra == 'all'
Provides-Extra: test
Requires-Dist: pytest >=3.6 ; extra == 'test'
Requires-Dist: pytest-cov ; extra == 'test'
Requires-Dist: coverage ; extra == 'test'
Requires-Dist: codecov ; extra == 'test'
Requires-Dist: pytest-benchmark ; extra == 'test'
Requires-Dist: black ; extra == 'test'
Requires-Dist: sphinx ; extra == 'test'
Requires-Dist: nbsphinx ; extra == 'test'
